sk_cv/__init__.py
sk_cv/__version__.py
sk_cv/image_io.py
sk_cv/image_processing.py
sk_dm/__init__.py
sk_dm/__version__.py
sk_dm/data_explore.py
sk_dm/data_model.py
sk_dm/data_prepare.py
sk_dm/feature_engineering.py
sk_dm/model_evaluation.py
sk_cv-0.2.5.dist-info/LICENSE
sk_cv-0.2.5.dist-info/METADATA
sk_cv-0.2.5.dist-info/WHEEL
sk_cv-0.2.5.dist-info/top_level.txt
sk_cv-0.2.5.dist-info/RECORD
