Metadata-Version: 2.1
Name: sk-cv
Version: 0.2.5
Summary: Image processing kit.
Home-page: https://github.com/me/myproject
Author: sunzongzong
Author-email: sunzongzong@mastercom.cn
License: MIT
Platform: UNKNOWN
Classifier: License :: OSI Approved :: MIT License
Classifier: Programming Language :: Python
Classifier: Programming Language :: Python :: 3
Classifier: Programming Language :: Python :: 3.6
Classifier: Programming Language :: Python :: Implementation :: CPython
Classifier: Programming Language :: Python :: Implementation :: PyPy
Requires-Python: >=3.6.0
License-File: LICENSE
